proto/__init__.py
proto/proto.py
proto_obj-0.0.4.dist-info/LICENSE
proto_obj-0.0.4.dist-info/METADATA
proto_obj-0.0.4.dist-info/WHEEL
proto_obj-0.0.4.dist-info/top_level.txt
proto_obj-0.0.4.dist-info/RECORD
