Metadata-Version: 2.1
Name: proto-obj
Version: 0.0.4
Summary: Proto is a small module for creating objects.
Author-email: Artic <artic.admisoffi@gmail.com>
Project-URL: Homepage, https://github.com/ArticOff/proto-obj
Classifier: Programming Language :: Python :: 3
Classifier: License :: OSI Approved :: GNU General Public License v3 (GPLv3)
Classifier: Operating System :: OS Independent
Requires-Python: >=3.10
License-File: LICENSE
